AUTHORS.rst
CHANGELOG.rst
LICENSE
MANIFEST.in
README.rst
setup.py
jmbo_video.egg-info/PKG-INFO
jmbo_video.egg-info/SOURCES.txt
jmbo_video.egg-info/dependency_links.txt
jmbo_video.egg-info/not-zip-safe
jmbo_video.egg-info/requires.txt
jmbo_video.egg-info/top_level.txt
video/__init__.py
video/admin.py
video/api.py
video/models.py
video/urls.py
video/templates/video/inclusion_tags/video_detail.html
video/tests/__init__.py
video/tests/__init__.pyc
video/tests/urls.py
video/tests/urls.pyc